MANIFEST.in
README.rst
setup.py
marionette_extension/__init__.py
marionette_extension/installer.py
marionette_extension/push_bundles.sh
marionette_extension.egg-info/PKG-INFO
marionette_extension.egg-info/SOURCES.txt
marionette_extension.egg-info/dependency_links.txt
marionette_extension.egg-info/entry_points.txt
marionette_extension.egg-info/not-zip-safe
marionette_extension.egg-info/requires.txt
marionette_extension.egg-info/top_level.txt
marionette_extension/bundles/1.3/marionette@mozilla.org/chrome.manifest
marionette_extension/bundles/1.3/marionette@mozilla.org/install.rdf
marionette_extension/bundles/1.3/marionette@mozilla.org/chrome/content/ChromeUtils.js
marionette_extension/bundles/1.3/marionette@mozilla.org/chrome/content/EventUtils.js
marionette_extension/bundles/1.3/marionette@mozilla.org/chrome/content/MozillaLogger.js
marionette_extension/bundles/1.3/marionette@mozilla.org/chrome/content/atoms.js
marionette_extension/bundles/1.3/marionette@mozilla.org/chrome/content/marionette-common.js
marionette_extension/bundles/1.3/marionette@mozilla.org/chrome/content/marionette-elements.js
marionette_extension/bundles/1.3/marionette@mozilla.org/chrome/content/marionette-frame-manager.js
marionette_extension/bundles/1.3/marionette@mozilla.org/chrome/content/marionette-listener.js
marionette_extension/bundles/1.3/marionette@mozilla.org/chrome/content/marionette-sendkeys.js
marionette_extension/bundles/1.3/marionette@mozilla.org/chrome/content/marionette-server.js
marionette_extension/bundles/1.3/marionette@mozilla.org/chrome/content/marionette-simpletest.js
marionette_extension/bundles/1.3/marionette@mozilla.org/components/marionetteextensioncomponent.js
marionette_extension/bundles/1.3/special-powers@mozilla.org/chrome.manifest
marionette_extension/bundles/1.3/special-powers@mozilla.org/install.rdf
marionette_extension/bundles/1.3/special-powers@mozilla.org/components/SpecialPowersObserver.js
marionette_extension/bundles/1.3/special-powers@mozilla.org/components/asdf
marionette_extension/bundles/1.3/special-powers@mozilla.org/content/MozillaLogger.js
marionette_extension/bundles/1.3/special-powers@mozilla.org/content/SpecialPowersObserver.js
marionette_extension/bundles/1.3/special-powers@mozilla.org/content/SpecialPowersObserverAPI.js
