Metadata-Version: 1.0
Name: marionette-extension
Version: 0.4.9
Summary: Installs Marionette as an extension on an FxOS device
Home-page: https://github.com/mozilla-b2g/fxos-certsuite
Author: Mozilla Automation and Testing Team
Author-email: tools@lists.mozilla.org
License: MPL
Keywords: mozilla
Platform: UNKNOWN
